cryoCOFI/__init__.py
cryoCOFI/_utils.py
cryoCOFI/average_z.py
cryoCOFI/bicanny.py
cryoCOFI/canny.py
cryoCOFI/carbon_film_detector.py
cryoCOFI/detector_for_cryosparc.py
cryoCOFI/detector_for_dynamo.py
cryoCOFI/detector_for_relion.py
cryoCOFI/find_highest_density.py
cryoCOFI/hough_transform.py
cryoCOFI/low_pass_filter.py
cryoCOFI/main.py
cryoCOFI/lib/__init__.py
cryoCOFI/lib/bilateral_filter.so
cryoCOFI/lib/canny.so
cryoCOFI/lib/edge_detector.so
cryoCOFI/lib/find_highest_density.so
cryoCOFI/lib/find_highest_density_double.so
cryoCOFI/lib/gaussian_filter.so
cryoCOFI/lib/hough_transform.so
cryoCOFI/lib/weighted_hough_transform.so
cryoCOFI-1.0.3.dist-info/LICENSE
cryoCOFI-1.0.3.dist-info/METADATA
cryoCOFI-1.0.3.dist-info/WHEEL
cryoCOFI-1.0.3.dist-info/entry_points.txt
cryoCOFI-1.0.3.dist-info/top_level.txt
cryoCOFI-1.0.3.dist-info/RECORD
