Metadata-Version: 2.1
Name: cryoCOFI
Version: 1.0.3
Summary: CarbOn FIlm detector for cryo-EM images
Home-page: https://github.com/ZhenHuangLab/cryoCOFI
Author: Zhen Huang
Author-email: zhen.victor.huang@gmail.com
License: GPLv3
Project-URL: Bug Reports, https://github.com/ZhenHuangLab/cryoCOFI/issues
Project-URL: Source, https://github.com/ZhenHuangLab/cryoCOFI
Keywords: cryo-EM,cryo-ET,carbon film,edge detection,CUDA,CuPy
Classifier: Programming Language :: Python :: 3
Classifier: License :: OSI Approved :: GNU General Public License v3 (GPLv3)
Classifier: Operating System :: OS Independent
Classifier: Development Status :: 5 - Production/Stable
Classifier: Environment :: GPU :: NVIDIA CUDA :: 12 :: 12.2
Requires-Python: >=3.9
License-File: LICENSE
Requires-Dist: cupy >=13.3.0
Requires-Dist: mrcfile >=1.5.3
Requires-Dist: matplotlib >=3.9.2
Requires-Dist: argparse
Requires-Dist: numpy >=2.0.2
Requires-Dist: tqdm >=4.66.5
Requires-Dist: pandas >=2.2.3
Requires-Dist: setproctitle >=1.3.3
Requires-Dist: starfile >=0.5.8
Requires-Dist: pyarrow >=18.0.0
